<annotation>
	<folder>forObjDet</folder>
	<filename>0140.jpg</filename>
	<path>C:\Users\Alexander\Documents\faces\New\test2\0140.jpg</path>
	<source>
		<database>Unknown</database>
	</source>
	<size>
		<width>320</width>
		<height>320</height>
		<depth>3</depth>
	</size>
	<segmented>0</segmented>
    <object>
		<name>pupil</name>
		<pose>Unspecified</pose>
		<truncated>0</truncated>
		<difficult>0</difficult>
		<bndbox>
			<xmin>159</xmin>
			<ymin>152</ymin>
			<xmax>189</xmax>
			<ymax>182</ymax>
		</bndbox>
	</object>
</annotation>